jmessage/__init__.py
jmessage/group.py
jmessage/im.py
jmessage/message.py
jmessage/report.py
jmessage/resource.py
jmessage/room.py
jmessage/sensitiveword.py
jmessage/user.py
jmessage-2.0.0.dist-info/DESCRIPTION.rst
jmessage-2.0.0.dist-info/METADATA
jmessage-2.0.0.dist-info/RECORD
jmessage-2.0.0.dist-info/WHEEL
jmessage-2.0.0.dist-info/metadata.json
jmessage-2.0.0.dist-info/top_level.txt
