Metadata-Version: 2.0
Name: jmessage
Version: 2.0.0
Summary: JMessage's officially supported Python client library
Home-page: https://github.com/jpush/jmessage-api-python-client
Author: jiguang
Author-email: support@jiguang.cn
License: The MIT License (MIT)
Requires-Dist: requests
